iauto/__init__.py
iauto/__main__.py
iauto/_asyncio.py
iauto/log.py
iauto/actions/__init__.py
iauto/actions/action.py
iauto/actions/executor.py
iauto/actions/loader.py
iauto/actions/playbook.py
iauto/actions/buildin/__init__.py
iauto/actions/buildin/collections.py
iauto/actions/buildin/db.py
iauto/actions/buildin/file.py
iauto/actions/buildin/flow.py
iauto/actions/buildin/hash.py
iauto/actions/buildin/json.py
iauto/actions/buildin/log.py
iauto/actions/buildin/math.py
iauto/actions/buildin/playbook.py
iauto/actions/buildin/queue.py
iauto/actions/buildin/shell.py
iauto/actions/buildin/time.py
iauto/actions/contrib/__init__.py
iauto/actions/contrib/browser.py
iauto/actions/contrib/webdriver.py
iauto/agents/__init__.py
iauto/agents/_actions.py
iauto/agents/executor.py
iauto/agents/model_clients.py
iauto/llms/__init__.py
iauto/llms/__main__.py
iauto/llms/_openai_qwen.py
iauto/llms/_qwen.py
iauto/llms/actions.py
iauto/llms/chatglm.py
iauto/llms/llama.py
iauto/llms/llm.py
iauto/llms/llm_factory.py
iauto/llms/openai.py
iauto/llms/session.py
iauto/playground/Agents.py
iauto/playground/__init__.py
iauto/playground/runner.py
iauto/playground/st_widgets.py
iauto/playground/utils.py
iauto/playground/pages/100_Settings.py
iauto/playground/pages/1_Playbooks.py
iauto/playground/pages/4_Actions.py
iauto/playground/pages/__init__.py
iauto/playground/playbooks/__init__.py
iauto/playground/playbooks/agents.yaml
iauto/playground/playbooks/llm_chat.yaml
iauto/playground/static/__init__.py
iauto/playground/static/ia.png
tests/__init__.py
tests/iauto/__init__.py
tests/iauto/actions/__init__.py
tests/iauto/actions/test_json.py
tests/iauto/actions/test_playbook.py
iauto-0.1.10.dist-info/LICENSE
iauto-0.1.10.dist-info/METADATA
iauto-0.1.10.dist-info/WHEEL
iauto-0.1.10.dist-info/entry_points.txt
iauto-0.1.10.dist-info/top_level.txt
iauto-0.1.10.dist-info/RECORD
