Metadata-Version: 2.1
Name: iauto
Version: 0.1.10
Summary: iauto is a low-code engine for building and deploying AI agents
Home-page: https://github.com/shellc/iauto
Author: shellc
Author-email: shenggong.wang@gmail.com
License: MIT
Keywords: AI,Automation,LLM,RPA
Classifier: Programming Language :: Python :: 3
Requires-Python: >=3.8
License-File: LICENSE
Requires-Dist: pydantic
Requires-Dist: PyYAML
Requires-Dist: python-dotenv
Requires-Dist: prompt-toolkit
Requires-Dist: openai
Requires-Dist: pyautogen
Requires-Dist: llama-cpp-python
Requires-Dist: playwright
Requires-Dist: Appium-Python-Client
Requires-Dist: SQLAlchemy
Requires-Dist: pandas
Requires-Dist: streamlit
Requires-Dist: watchdog
